plankalkul/__init__.py
plankalkul/interpreter.py
plankalkul-0.2.1.dist-info/licenses/LICENSE
plankalkul-0.2.1.dist-info/METADATA
plankalkul-0.2.1.dist-info/WHEEL
plankalkul-0.2.1.dist-info/entry_points.txt
plankalkul-0.2.1.dist-info/top_level.txt
plankalkul-0.2.1.dist-info/RECORD
