Metadata-Version: 2.4
Name: plankalkul
Version: 0.2.1
Summary: Interpreter for Plankalkul, the first high-level programming language (Konrad Zuse, 1945)
Author-email: Zane Hambly <wxq1807@autuni.ac.nz>
Maintainer: The Ian Index
License: MIT
Project-URL: Homepage, https://github.com/Zaneham/Plankalkul
Project-URL: Documentation, https://github.com/Zaneham/Plankalkul#readme
Project-URL: Repository, https://github.com/Zaneham/Plankalkul
Project-URL: Bug Tracker, https://github.com/Zaneham/Plankalkul/issues
Project-URL: Zuse Chess, https://zaneham.github.io/zuse-chess-1942/
Keywords: plankalkul,zuse,historical,programming-language,interpreter,1945
Classifier: Development Status :: 4 - Beta
Classifier: Intended Audience :: Developers
Classifier: Intended Audience :: Education
Classifier: Intended Audience :: Science/Research
Classifier: License :: OSI Approved :: MIT License
Classifier: Operating System :: OS Independent
Classifier: Programming Language :: Python :: 3
Classifier: Programming Language :: Python :: 3.8
Classifier: Programming Language :: Python :: 3.9
Classifier: Programming Language :: Python :: 3.10
Classifier: Programming Language :: Python :: 3.11
Classifier: Programming Language :: Python :: 3.12
Classifier: Topic :: Software Development :: Interpreters
Classifier: Topic :: Education
Classifier: Topic :: Scientific/Engineering
Requires-Python: >=3.8
License-File: LICENSE
Dynamic: license-file
